python_crisp/__init__.py
python_crisp/__version__.py
python_crisp/errors/__init__.py
python_crisp/errors/route.py
python_crisp/resources/__init__.py
python_crisp/resources/bucket.py
python_crisp/resources/plugin.py
python_crisp/resources/website.py
python_crisp-1.0.1.dist-info/LICENSE
python_crisp-1.0.1.dist-info/METADATA
python_crisp-1.0.1.dist-info/WHEEL
python_crisp-1.0.1.dist-info/top_level.txt
python_crisp-1.0.1.dist-info/RECORD
