Metadata-Version: 2.1
Name: python-crisp
Version: 1.0.1
Summary: Crisp API Python.
Home-page: https://github.com/lvillis/python-crisp-api
Author: Lvillis
Author-email: lvillis@outlook.com
License: MIT
Download-URL: https://github.com/lvillis/python-crisp-api/releases
Platform: UNKNOWN
Classifier: Intended Audience :: Developers
Classifier: Natural Language :: English
Classifier: License :: OSI Approved :: MIT License
Classifier: Programming Language :: Python :: 3.6
Classifier: Programming Language :: Python :: 3.7
Classifier: Programming Language :: Python :: 3.8
Classifier: Programming Language :: Python :: 3.9
License-File: LICENSE
Requires-Dist: requests
